adaptive_solve_planner/__init__.py
adaptive_solve_planner/annotated_original.py
adaptive_solve_planner/api.py
adaptive_solve_planner/autotune.py
adaptive_solve_planner/config.py
adaptive_solve_planner/core.py
adaptive_solve_planner/tools.py
adaptive_solve_planner/utils.py
adaptive_solve_planner/worker.py
adaptivesolveplanner-0.1.0.dist-info/METADATA
adaptivesolveplanner-0.1.0.dist-info/WHEEL
adaptivesolveplanner-0.1.0.dist-info/top_level.txt
adaptivesolveplanner-0.1.0.dist-info/RECORD
