Metadata-Version: 2.4
Name: adaptivesolveplanner
Version: 0.1.0
Summary: Adaptive tournament planning engine
Author: SmokiCool
Author-email: SmokiCool <none@example.com>
License: MIT
Classifier: Programming Language :: Python
Classifier: Programming Language :: Python :: 3
Classifier: License :: OSI Approved :: MIT License
Classifier: Intended Audience :: Developers
Requires-Python: >=3.11
Requires-Dist: pydantic<3,>=2.6
Requires-Dist: pydantic-settings<3,>=2.0
